SaidouNeurones/ReseauNeuronesSaid.py
SaidouNeurones/SaidouNeuroneV2.py
SaidouNeurones/SaidouNeuroneV3.py
SaidouNeurones/__init__.py
SaidouNeurones/tests/__init__.py
SaidouNeurones/tests/test_saidou_neurone_v3.py
SaidouPixels/Pixels.py
SaidouPixels/__init__.py
saidoumodule-1.3.0.dist-info/METADATA
saidoumodule-1.3.0.dist-info/WHEEL
saidoumodule-1.3.0.dist-info/top_level.txt
saidoumodule-1.3.0.dist-info/RECORD
