Metadata-Version: 2.4
Name: SaidouModule
Version: 1.3.0
Summary: Module contenant des outils de réseaux de neurones simples et de manipulation d'images pixelisées.
Home-page: https://github.com/SMedd69/SaidouModule
Author: Meddahi Saïd
Author-email: s.meddahi.fo@gmail.com
Classifier: Development Status :: 4 - Beta
Classifier: License :: OSI Approved :: MIT License
Classifier: Programming Language :: Python :: 3
Classifier: Programming Language :: Python :: 3.7
Classifier: Programming Language :: Python :: 3.8
Requires-Python: >=3.7
Requires-Dist: numpy
Requires-Dist: matplotlib
Requires-Dist: opencv-python
Requires-Dist: tqdm
Requires-Dist: scikit-learn
